{"email": "Najla.daoud@esprit.tn", "phone": "(+216) 53075584", "name": "Internet Technology", "total_exp": 7, "university": [], "designition": ["student", "devops", "virtual assistant", "summer internship"], "degree": [], "skills": ["Programming language: Java ", "C ", "Python ", " C#", "web development : HTML", " CSS", " Javascript", "Typescript", "", "JQuery", " SASS", " BOOTSTRAP", " Angular", " ReactJs", "Laravel", " SpringBoot ", " NodeJs", " Express", " .net", " Django", "UML modelisation", "Data base management: Mysql", " MongoDB", " H2", "DevOps: Docker", " Git", " Nexus", " SonarQube", " Jenkins", "English : Level B1", "German : Level B1", "French: Level B2", "CONTACT", "(+216) 53075584", "INTERNSHIP AND PROJECTS", "HOBBIES", "Hiking", "Cycling", "Najla.daoud@esprit.tn", "Dar Chaaben", "Nabeul", "/in/najla-daoud-0762a4160/", "2019-2022: The Private Higher School of Engineering and", "Technology :Esprit", "2015-2018: Higher Institute of Transport and Logistics (ISTLS)", "2015:Secondary High School 14 Janvier", "DISTRIBUTED WEB PROJECT", " 2021 (2 months)", "Detail: Implementation of an airline application", "Work environment: Angular - SpringBoot - H2 Database -MicroService -", "Docker - Git", "SUMMER INTERNSHIP | INETUM", "Detail: Recruitment Tracking Application", "Work environment: Angular - SpringBoot - Mysql -Git", "github.com/najladaoud", "https://context.reverso.net/traduction/anglais-francais/Work+environment"], "Companies worked at": ["SKY TRAVEL"]}